yolort/__init__.py
yolort/version.py
yolort/data/__init__.py
yolort/data/_helper.py
yolort/data/builtin_meta.py
yolort/data/coco.py
yolort/data/coco_eval.py
yolort/data/data_module.py
yolort/data/distributed.py
yolort/data/transforms.py
yolort/data/voc.py
yolort/models/__init__.py
yolort/models/_checkpoint.py
yolort/models/_utils.py
yolort/models/anchor_utils.py
yolort/models/backbone_utils.py
yolort/models/box_head.py
yolort/models/darknet.py
yolort/models/darknetv4.py
yolort/models/darknetv6.py
yolort/models/path_aggregation_network.py
yolort/models/transform.py
yolort/models/transformer.py
yolort/models/yolo.py
yolort/models/yolo_lite.py
yolort/models/yolov5.py
yolort/relay/__init__.py
yolort/relay/ir_visualizer.py
yolort/relay/logits_decoder.py
yolort/relay/trace_wrapper.py
yolort/relay/trt_graphsurgeon.py
yolort/relay/trt_inference.py
yolort/runtime/__init__.py
yolort/runtime/ort_helper.py
yolort/runtime/trt_helper.py
yolort/runtime/y_onnxruntime.py
yolort/runtime/y_tensorrt.py
yolort/trainer/__init__.py
yolort/trainer/lightning_task.py
yolort/utils/__init__.py
yolort/utils/annotations_converter.py
yolort/utils/dependency.py
yolort/utils/hooks.py
yolort/utils/image_utils.py
yolort/utils/logger.py
yolort/utils/visualizer.py
yolort/v5/__init__.py
yolort/v5/helper.py
yolort/v5/models/__init__.py
yolort/v5/models/common.py
yolort/v5/models/experimental.py
yolort/v5/models/yolo.py
yolort/v5/utils/__init__.py
yolort/v5/utils/activations.py
yolort/v5/utils/augmentations.py
yolort/v5/utils/autoanchor.py
yolort/v5/utils/callbacks.py
yolort/v5/utils/datasets.py
yolort/v5/utils/downloads.py
yolort/v5/utils/general.py
yolort/v5/utils/loss.py
yolort/v5/utils/metrics.py
yolort/v5/utils/plots.py
yolort/v5/utils/torch_utils.py
yolort-0.6.3.dist-info/LICENSE
yolort-0.6.3.dist-info/METADATA
yolort-0.6.3.dist-info/WHEEL
yolort-0.6.3.dist-info/top_level.txt
yolort-0.6.3.dist-info/RECORD
