Metadata-Version: 2.1
Name: yolort
Version: 0.6.3
Summary: yolort is a runtime stack for object detection on specialized accelerators.
Home-page: https://github.com/zhiqwang/yolov5-rt-stack
Author: Zhiqiang Wang
Author-email: me@zhiqwang.com
License: GPL-3.0
Project-URL: Bug Reports, https://github.com/zhiqwang/yolov5-rt-stack/issues
Project-URL: Funding, https://zhiqwang.com
Project-URL: Source, https://github.com/zhiqwang/yolov5-rt-stack/
Keywords: machine-learning,deep-learning,ml,pytorch,YOLO,object-detection,YOLOv5,TorchScript
Platform: UNKNOWN
Classifier: Operating System :: OS Independent
Classifier: Development Status :: 4 - Beta
Classifier: Intended Audience :: Developers
Classifier: Topic :: Education
Classifier: Topic :: Scientific/Engineering
Classifier: Topic :: Scientific/Engineering :: Artificial Intelligence
Classifier: Topic :: Scientific/Engineering :: Image Recognition
Classifier: License :: OSI Approved :: GNU General Public License v3 (GPLv3)
Classifier: Programming Language :: Python :: 3
Classifier: Programming Language :: Python :: 3.6
Classifier: Programming Language :: Python :: 3.7
Classifier: Programming Language :: Python :: 3.8
Classifier: Programming Language :: Python :: 3.9
Classifier: Programming Language :: Python :: 3.10
Requires-Python: >=3.6
License-File: LICENSE
Requires-Dist: matplotlib (>=3.2.2)
Requires-Dist: numpy (>=1.18.5)
Requires-Dist: Pillow (>=8.0.0)
Requires-Dist: PyYAML (>=5.3.1)
Requires-Dist: scipy (>=1.4.1)
Requires-Dist: tqdm (>=4.41.0)
Requires-Dist: onnx (>=1.8.0)
Requires-Dist: ipython
Requires-Dist: tabulate
Requires-Dist: pandas
Requires-Dist: thop
